GradleShizhan/README.md
GradleShizhan/__init__.py
GradleShizhan/__main__.py
GradleShizhan/file.epub
GradleShizhan/index.html
GradleShizhan/css/__init__.py
GradleShizhan/css/annotations.css
GradleShizhan/css/main.css
GradleShizhan/css/normalize.css
GradleShizhan/css/popup.css
GradleShizhan/font/__init__.py
GradleShizhan/font/fontello.eot
GradleShizhan/font/fontello.svg
GradleShizhan/font/fontello.ttf
GradleShizhan/font/fontello.woff
GradleShizhan/img/__init__.py
GradleShizhan/img/annotator-glyph-sprite.png
GradleShizhan/img/annotator-icon-sprite.png
GradleShizhan/img/apple-touch-icon.png
GradleShizhan/img/cancelfullscreen.png
GradleShizhan/img/close.png
GradleShizhan/img/fullscreen.png
GradleShizhan/img/loader.gif
GradleShizhan/img/menu-icon.png
GradleShizhan/img/save.png
GradleShizhan/img/saved.png
GradleShizhan/img/settings-s.png
GradleShizhan/img/settings.png
GradleShizhan/img/star.png
GradleShizhan/js/__init__.py
GradleShizhan/js/epub.js
GradleShizhan/js/epub.min.js
GradleShizhan/js/epub.min.map
GradleShizhan/js/hooks.min.js
GradleShizhan/js/hooks.min.map
GradleShizhan/js/reader.js
GradleShizhan/js/reader.js.map
GradleShizhan/js/reader.min.js
GradleShizhan/js/reader.min.map
GradleShizhan/js/hooks/__init__.py
GradleShizhan/js/hooks/extensions/__init__.py
GradleShizhan/js/hooks/extensions/highlight.js
GradleShizhan/js/libs/__init__.py
GradleShizhan/js/libs/jquery.min.js
GradleShizhan/js/libs/localforage.min.js
GradleShizhan/js/libs/screenfull.js
GradleShizhan/js/libs/screenfull.min.js
GradleShizhan/js/libs/zip.min.js
GradleShizhan/js/plugins/__init__.py
GradleShizhan/js/plugins/hypothesis.js
GradleShizhan/js/plugins/search.js
gradle_shizhan-2024.3.4.0.dist-info/METADATA
gradle_shizhan-2024.3.4.0.dist-info/WHEEL
gradle_shizhan-2024.3.4.0.dist-info/entry_points.txt
gradle_shizhan-2024.3.4.0.dist-info/top_level.txt
gradle_shizhan-2024.3.4.0.dist-info/RECORD
